Workbook

Sheet README
A1: PCS Platform — Pricing & ARR Model
A3: TABS
A4: • US Assumptions / US ARR Model / US Unit Economics — North-American pricing in USD
A5: • India Assumptions / India ARR Model / India Unit Economics — India pricing in INR (ex-GST)
A7: HOW TO USE
A8: • Edit only the BLUE cells on an Assumptions tab. Everything else is a formula.
A9: • ARR rolls each segment's bookings forward by NRR and sums Low/Base/High scenarios.
A10: • Unit Economics derives gross margin, CAC payback and LTV:CAC; CAD-conversion compute is broken out as COGS.
A12: MODEL LOGIC
A13: • Metric = price per production SITE; floor/operator access unlimited, only office/admin seats counted.
A14: • Ending ARR(t) = Ending ARR(t-1) × NRR + new-logo ARR(t), per segment then summed.
A15: • LTV = annual gross profit ÷ logo churn (no expansion credit — conservative).
... A27: • See PRICING.md for the narrative one-pager and the per-tier feature matrix this model backs.

Sheet US Assumptions
A1: Model Assumptions (USD) — edit the blue cells
A3: PRICING (per site / year)
A4: Core MES | B4: 12000
A5: Quality & Traceability | B5: 30000
A6: Digital Twin / AR | B6: 54000
A7: Office/admin seat / yr | B7: 720
A9: SEGMENT ECONOMICS
A10: SMB blended ACV | B10: 22000
A11: Mid-market blended ACV | B11: 150000
A12: SMB onboarding (one-time) | B12: 7500
A13: Mid onboarding (one-time) | B13: 20000
A15: RETENTION
A16: SMB net revenue retention | B16: 1
A17: Mid NRR | B17: 1.15
A18: SMB logo churn / yr | B18: 0.15
A19: Mid logo churn / yr | B19: 0.08
A21: NEW-LOGO PLAN (Base scenario)
B22: Y1 | C22: Y2 | D22: Y3
A23: SMB new logos | B23: 12 | C23: 25 | D23: 40
A24: Mid new logos | B24: 2 | C24: 5 | D24: 9
A26: SCENARIO MULTIPLIERS
B27: Low | C27: Base | D27: High
A28: × Base plan | B28: 0.6 | C28: 1 | D28: 1.5
A30: UNIT ECONOMICS INPUTS
A31: SMB CAC per logo | B31: 8000
A32: Mid CAC per logo | B32: 45000
A33: Onboarding gross margin % | B33: 0.4
A35: COGS per SITE / year
A36: Hosting & infra (USD-priced) | B36: 1200
A37: CAD-conversion compute (USD-priced) | B37: 1500
A38: Support / CS | B38: 2000
A39: Payment processing (% of ACV) | B39: 0.025
A41: SITES PER CUSTOMER
A42: SMB sites | B42: 1
A43: Mid sites | B43: 4

Sheet US ARR Model
A1: ARR Model — ending ARR by scenario (US)
A3: ENDING ARR BY SCENARIO
B4: Y1 | C4: Y2 | D4: Y3
A5: Low | B5: =B20 | C5: =C20 | D5: =D20
A6: Base | B6: =B32 | C6: =C32 | D6: =D32
A7: High | B7: =B44 | C7: =C44 | D7: =D44
A9: Services revenue (one-time, Base) | B9: =B33 | C9: =C33 | D9: =D33
A12: LOW SCENARIO
B13: Y1 | C13: Y2 | D13: Y3
A14: SMB new logos | B14: =ROUND('US Assumptions'!B23*'US Assumptions'!$B$28,0) | C14: =ROUND('US Assumptions'!C23*'US Assumptions'!$B$28,0) | D14: =ROUND('US Assumptions'!D23*'US Assumptions'!$B$28,0)
A15: Mid new logos | B15: =ROUND('US Assumptions'!B24*'US Assumptions'!$B$28,0) | C15: =ROUND('US Assumptions'!C24*'US Assumptions'!$B$28,0) | D15: =ROUND('US Assumptions'!D24*'US Assumptions'!$B$28,0)
A16: SMB new ARR | B16: =B14*'US Assumptions'!$B$10 | C16: =C14*'US Assumptions'!$B$10 | D16: =D14*'US Assumptions'!$B$10
A17: Mid new ARR | B17: =B15*'US Assumptions'!$B$11 | C17: =C15*'US Assumptions'!$B$11 | D17: =D15*'US Assumptions'!$B$11
A18: SMB ending ARR | B18: =B16 | C18: =B18*'US Assumptions'!$B$16+C16 | D18: =C18*'US Assumptions'!$B$16+D16
A19: Mid ending ARR | B19: =B17 | C19: =B19*'US Assumptions'!$B$17+C17 | D19: =C19*'US Assumptions'!$B$17+D17
A20: Total ending ARR | B20: =B18+B19 | C20: =C18+C19 | D20: =D18+D19
A21: Services (one-time) | B21: =B14*'US Assumptions'!$B$12+B15*'US Assumptions'!$B$13 | C21: =C14*'US Assumptions'!$B$12+C15*'US Assumptions'!$B$13 | D21: =D14*'US Assumptions'!$B$12+D15*'US Assumptions'!$B$13
A24: BASE SCENARIO
B25: Y1 | C25: Y2 | D25: Y3
A26: SMB new logos | B26: =ROUND('US Assumptions'!B23*'US Assumptions'!$C$28,0) | C26: =ROUND('US Assumptions'!C23*'US Assumptions'!$C$28,0) | D26: =ROUND('US Assumptions'!D23*'US Assumptions'!$C$28,0)
A27: Mid new logos | B27: =ROUND('US Assumptions'!B24*'US Assumptions'!$C$28,0) | C27: =ROUND('US Assumptions'!C24*'US Assumptions'!$C$28,0) | D27: =ROUND('US Assumptions'!D24*'US Assumptions'!$C$28,0)
A28: SMB new ARR | B28: =B26*'US Assumptions'!$B$10 | C28: =C26*'US Assumptions'!$B$10 | D28: =D26*'US Assumptions'!$B$10
A29: Mid new ARR | B29: =B27*'US Assumptions'!$B$11 | C29: =C27*'US Assumptions'!$B$11 | D29: =D27*'US Assumptions'!$B$11
A30: SMB ending ARR | B30: =B28 | C30: =B30*'US Assumptions'!$B$16+C28 | D30: =C30*'US Assumptions'!$B$16+D28
A31: Mid ending ARR | B31: =B29 | C31: =B31*'US Assumptions'!$B$17+C29 | D31: =C31*'US Assumptions'!$B$17+D29
A32: Total ending ARR | B32: =B30+B31 | C32: =C30+C31 | D32: =D30+D31
A33: Services (one-time) | B33: =B26*'US Assumptions'!$B$12+B27*'US Assumptions'!$B$13 | C33: =C26*'US Assumptions'!$B$12+C27*'US Assumptions'!$B$13 | D33: =D26*'US Assumptions'!$B$12+D27*'US Assumptions'!$B$13
A36: HIGH SCENARIO
B37: Y1 | C37: Y2 | D37: Y3
A38: SMB new logos | B38: =ROUND('US Assumptions'!B23*'US Assumptions'!$D$28,0) | C38: =ROUND('US Assumptions'!C23*'US Assumptions'!$D$28,0) | D38: =ROUND('US Assumptions'!D23*'US Assumptions'!$D$28,0)
A39: Mid new logos | B39: =ROUND('US Assumptions'!B24*'US Assumptions'!$D$28,0) | C39: =ROUND('US Assumptions'!C24*'US Assumptions'!$D$28,0) | D39: =ROUND('US Assumptions'!D24*'US Assumptions'!$D$28,0)
A40: SMB new ARR | B40: =B38*'US Assumptions'!$B$10 | C40: =C38*'US Assumptions'!$B$10 | D40: =D38*'US Assumptions'!$B$10
A41: Mid new ARR | B41: =B39*'US Assumptions'!$B$11 | C41: =C39*'US Assumptions'!$B$11 | D41: =D39*'US Assumptions'!$B$11
A42: SMB ending ARR | B42: =B40 | C42: =B42*'US Assumptions'!$B$16+C40 | D42: =C42*'US Assumptions'!$B$16+D40
A43: Mid ending ARR | B43: =B41 | C43: =B43*'US Assumptions'!$B$17+C41 | D43: =C43*'US Assumptions'!$B$17+D41
A44: Total ending ARR | B44: =B42+B43 | C44: =C42+C43 | D44: =D42+D43
A45: Services (one-time) | B45: =B38*'US Assumptions'!$B$12+B39*'US Assumptions'!$B$13 | C45: =C38*'US Assumptions'!$B$12+C39*'US Assumptions'!$B$13 | D45: =D38*'US Assumptions'!$B$12+D39*'US Assumptions'!$B$13

Sheet US Unit Economics
A1: Unit Economics (US)
A3: Metric | B3: SMB | C3: Mid | D3: Blended | E3: weights | F3: n
A4: ACV / yr | B4: ='US Assumptions'!B10 | C4: ='US Assumptions'!B11 | D4: =(B4*$F$4+C4*$F$5)/($F$4+$F$5) | E4: SMB logos (Base) | F4: =SUM('US Assumptions'!B23:D23)
A5: Sites per customer | B5: ='US Assumptions'!B42 | C5: ='US Assumptions'!B43 | E5: Mid logos (Base) | F5: =SUM('US Assumptions'!B24:D24)
A6: COGS — hosting & infra | B6: =B5*'US Assumptions'!$B$36 | C6: =C5*'US Assumptions'!$B$36
A7: COGS — CAD-conversion compute | B7: =B5*'US Assumptions'!$B$37 | C7: =C5*'US Assumptions'!$B$37
A8: COGS — support / CS | B8: =B5*'US Assumptions'!$B$38 | C8: =C5*'US Assumptions'!$B$38
A9: COGS — payments | B9: =B4*'US Assumptions'!$B$39 | C9: =C4*'US Assumptions'!$B$39
A10: Total COGS | B10: =SUM(B6:B9) | C10: =SUM(C6:C9) | D10: =(B10*$F$4+C10*$F$5)/($F$4+$F$5)
A11: Gross profit / yr | B11: =B4-B10 | C11: =C4-C10 | D11: =(B11*$F$4+C11*$F$5)/($F$4+$F$5)
A12: Gross margin % | B12: =B11/B4 | C12: =C11/C4 | D12: =D11/D4
A14: CAC per logo | B14: ='US Assumptions'!B31 | C14: ='US Assumptions'!B32 | D14: =(B14*$F$4+C14*$F$5)/($F$4+$F$5)
A15: Onboarding fee | B15: ='US Assumptions'!B12 | C15: ='US Assumptions'!B13
A16: Onboarding gross profit | B16: =B15*'US Assumptions'!$B$33 | C16: =C15*'US Assumptions'!$B$33
A17: Net CAC (CAC − onb. GP) | B17: =B14-B16 | C17: =C14-C16 | D17: =(B17*$F$4+C17*$F$5)/($F$4+$F$5)
A19: Monthly gross profit | B19: =B11/12 | C19: =C11/12
A20: CAC payback (gross) | B20: =B14/B19 | C20: =C14/C19 | D20: =D14/(D11/12)
A21: Net CAC payback | B21: =B17/B19 | C21: =C17/C19 | D21: =D17/(D11/12)
A23: Logo churn / yr | B23: ='US Assumptions'!B18 | C23: ='US Assumptions'!B19
A24: Customer lifetime (yrs) | B24: =1/B23 | C24: =1/C23
A25: LTV (gross margin) | B25: =B11*B24 | C25: =C11*C24 | D25: =(B25*$F$4+C25*$F$5)/($F$4+$F$5)
A26: LTV:CAC (gross) | B26: =B25/B14 | C26: =C25/C14 | D26: =D25/D14
A27: LTV:CAC (net CAC) | B27: =B25/B17 | C27: =C25/C17 | D27: =D25/D17

Sheet India Assumptions
A1: Model Assumptions (INR, ex-GST) — edit the blue cells
A3: PRICING (per site / year)
A4: Core MES | B4: 144000
A5: Quality & Traceability | B5: 360000
A6: Digital Twin / AR | B6: 600000
A7: Office/admin seat / yr | B7: 10800
A9: SEGMENT ECONOMICS
A10: SMB blended ACV | B10: 250000
A11: Mid-market blended ACV | B11: 1750000
A12: SMB onboarding (one-time) | B12: 50000
A13: Mid onboarding (one-time) | B13: 350000
A15: RETENTION
A16: SMB net revenue retention | B16: 0.95
A17: Mid NRR | B17: 1.1
A18: SMB logo churn / yr | B18: 0.2
A19: Mid logo churn / yr | B19: 0.1
A21: NEW-LOGO PLAN (Base scenario)
B22: Y1 | C22: Y2 | D22: Y3
A23: SMB new logos | B23: 20 | C23: 50 | D23: 90
A24: Mid new logos | B24: 3 | C24: 8 | D24: 15
A26: SCENARIO MULTIPLIERS
B27: Low | C27: Base | D27: High
A28: × Base plan | B28: 0.6 | C28: 1 | D28: 1.5
A30: UNIT ECONOMICS INPUTS
A31: SMB CAC per logo | B31: 125000
A32: Mid CAC per logo | B32: 800000
A33: Onboarding gross margin % | B33: 0.4
A35: COGS per SITE / year
A36: Hosting & infra (USD-priced) | B36: 35000
A37: CAD-conversion compute (USD-priced) | B37: 100000
A38: Support / CS | B38: 20000
A39: Payment processing (% of ACV) | B39: 0.02
A41: SITES PER CUSTOMER
A42: SMB sites | B42: 1
A43: Mid sites | B43: 4

Sheet India ARR Model
A1: ARR Model — ending ARR by scenario (India)
A3: ENDING ARR BY SCENARIO
B4: Y1 | C4: Y2 | D4: Y3
A5: Low | B5: =B20 | C5: =C20 | D5: =D20
A6: Base | B6: =B32 | C6: =C32 | D6: =D32
A7: High | B7: =B44 | C7: =C44 | D7: =D44
A9: Services revenue (one-time, Base) | B9: =B33 | C9: =C33 | D9: =D33
A12: LOW SCENARIO
B13: Y1 | C13: Y2 | D13: Y3
A14: SMB new logos | B14: =ROUND('India Assumptions'!B23*'India Assumptions'!$B$28,0) | C14: =ROUND('India Assumptions'!C23*'India Assumptions'!$B$28,0) | D14: =ROUND('India Assumptions'!D23*'India Assumptions'!$B$28,0)
A15: Mid new logos | B15: =ROUND('India Assumptions'!B24*'India Assumptions'!$B$28,0) | C15: =ROUND('India Assumptions'!C24*'India Assumptions'!$B$28,0) | D15: =ROUND('India Assumptions'!D24*'India Assumptions'!$B$28,0)
A16: SMB new ARR | B16: =B14*'India Assumptions'!$B$10 | C16: =C14*'India Assumptions'!$B$10 | D16: =D14*'India Assumptions'!$B$10
A17: Mid new ARR | B17: =B15*'India Assumptions'!$B$11 | C17: =C15*'India Assumptions'!$B$11 | D17: =D15*'India Assumptions'!$B$11
A18: SMB ending ARR | B18: =B16 | C18: =B18*'India Assumptions'!$B$16+C16 | D18: =C18*'India Assumptions'!$B$16+D16
A19: Mid ending ARR | B19: =B17 | C19: =B19*'India Assumptions'!$B$17+C17 | D19: =C19*'India Assumptions'!$B$17+D17
A20: Total ending ARR | B20: =B18+B19 | C20: =C18+C19 | D20: =D18+D19
A21: Services (one-time) | B21: =B14*'India Assumptions'!$B$12+B15*'India Assumptions'!$B$13 | C21: =C14*'India Assumptions'!$B$12+C15*'India Assumptions'!$B$13 | D21: =D14*'India Assumptions'!$B$12+D15*'India Assumptions'!$B$13
A24: BASE SCENARIO
B25: Y1 | C25: Y2 | D25: Y3
A26: SMB new logos | B26: =ROUND('India Assumptions'!B23*'India Assumptions'!$C$28,0) | C26: =ROUND('India Assumptions'!C23*'India Assumptions'!$C$28,0) | D26: =ROUND('India Assumptions'!D23*'India Assumptions'!$C$28,0)
A27: Mid new logos | B27: =ROUND('India Assumptions'!B24*'India Assumptions'!$C$28,0) | C27: =ROUND('India Assumptions'!C24*'India Assumptions'!$C$28,0) | D27: =ROUND('India Assumptions'!D24*'India Assumptions'!$C$28,0)
A28: SMB new ARR | B28: =B26*'India Assumptions'!$B$10 | C28: =C26*'India Assumptions'!$B$10 | D28: =D26*'India Assumptions'!$B$10
A29: Mid new ARR | B29: =B27*'India Assumptions'!$B$11 | C29: =C27*'India Assumptions'!$B$11 | D29: =D27*'India Assumptions'!$B$11
A30: SMB ending ARR | B30: =B28 | C30: =B30*'India Assumptions'!$B$16+C28 | D30: =C30*'India Assumptions'!$B$16+D28
A31: Mid ending ARR | B31: =B29 | C31: =B31*'India Assumptions'!$B$17+C29 | D31: =C31*'India Assumptions'!$B$17+D29
A32: Total ending ARR | B32: =B30+B31 | C32: =C30+C31 | D32: =D30+D31
A33: Services (one-time) | B33: =B26*'India Assumptions'!$B$12+B27*'India Assumptions'!$B$13 | C33: =C26*'India Assumptions'!$B$12+C27*'India Assumptions'!$B$13 | D33: =D26*'India Assumptions'!$B$12+D27*'India Assumptions'!$B$13
A36: HIGH SCENARIO
B37: Y1 | C37: Y2 | D37: Y3
A38: SMB new logos | B38: =ROUND('India Assumptions'!B23*'India Assumptions'!$D$28,0) | C38: =ROUND('India Assumptions'!C23*'India Assumptions'!$D$28,0) | D38: =ROUND('India Assumptions'!D23*'India Assumptions'!$D$28,0)
A39: Mid new logos | B39: =ROUND('India Assumptions'!B24*'India Assumptions'!$D$28,0) | C39: =ROUND('India Assumptions'!C24*'India Assumptions'!$D$28,0) | D39: =ROUND('India Assumptions'!D24*'India Assumptions'!$D$28,0)
A40: SMB new ARR | B40: =B38*'India Assumptions'!$B$10 | C40: =C38*'India Assumptions'!$B$10 | D40: =D38*'India Assumptions'!$B$10
A41: Mid new ARR | B41: =B39*'India Assumptions'!$B$11 | C41: =C39*'India Assumptions'!$B$11 | D41: =D39*'India Assumptions'!$B$11
A42: SMB ending ARR | B42: =B40 | C42: =B42*'India Assumptions'!$B$16+C40 | D42: =C42*'India Assumptions'!$B$16+D40
A43: Mid ending ARR | B43: =B41 | C43: =B43*'India Assumptions'!$B$17+C41 | D43: =C43*'India Assumptions'!$B$17+D41
A44: Total ending ARR | B44: =B42+B43 | C44: =C42+C43 | D44: =D42+D43
A45: Services (one-time) | B45: =B38*'India Assumptions'!$B$12+B39*'India Assumptions'!$B$13 | C45: =C38*'India Assumptions'!$B$12+C39*'India Assumptions'!$B$13 | D45: =D38*'India Assumptions'!$B$12+D39*'India Assumptions'!$B$13

Sheet India Unit Economics
A1: Unit Economics (India)
A3: Metric | B3: SMB | C3: Mid | D3: Blended | E3: weights | F3: n
A4: ACV / yr | B4: ='India Assumptions'!B10 | C4: ='India Assumptions'!B11 | D4: =(B4*$F$4+C4*$F$5)/($F$4+$F$5) | E4: SMB logos (Base) | F4: =SUM('India Assumptions'!B23:D23)
A5: Sites per customer | B5: ='India Assumptions'!B42 | C5: ='India Assumptions'!B43 | E5: Mid logos (Base) | F5: =SUM('India Assumptions'!B24:D24)
A6: COGS — hosting & infra | B6: =B5*'India Assumptions'!$B$36 | C6: =C5*'India Assumptions'!$B$36
A7: COGS — CAD-conversion compute | B7: =0 | C7: =C5*'India Assumptions'!$B$37
A8: COGS — support / CS | B8: =B5*'India Assumptions'!$B$38 | C8: =C5*'India Assumptions'!$B$38
A9: COGS — payments | B9: =B4*'India Assumptions'!$B$39 | C9: =C4*'India Assumptions'!$B$39
A10: Total COGS | B10: =SUM(B6:B9) | C10: =SUM(C6:C9) | D10: =(B10*$F$4+C10*$F$5)/($F$4+$F$5)
A11: Gross profit / yr | B11: =B4-B10 | C11: =C4-C10 | D11: =(B11*$F$4+C11*$F$5)/($F$4+$F$5)
A12: Gross margin % | B12: =B11/B4 | C12: =C11/C4 | D12: =D11/D4
A14: CAC per logo | B14: ='India Assumptions'!B31 | C14: ='India Assumptions'!B32 | D14: =(B14*$F$4+C14*$F$5)/($F$4+$F$5)
A15: Onboarding fee | B15: ='India Assumptions'!B12 | C15: ='India Assumptions'!B13
A16: Onboarding gross profit | B16: =B15*'India Assumptions'!$B$33 | C16: =C15*'India Assumptions'!$B$33
A17: Net CAC (CAC − onb. GP) | B17: =B14-B16 | C17: =C14-C16 | D17: =(B17*$F$4+C17*$F$5)/($F$4+$F$5)
A19: Monthly gross profit | B19: =B11/12 | C19: =C11/12
A20: CAC payback (gross) | B20: =B14/B19 | C20: =C14/C19 | D20: =D14/(D11/12)
A21: Net CAC payback | B21: =B17/B19 | C21: =C17/C19 | D21: =D17/(D11/12)
A23: Logo churn / yr | B23: ='India Assumptions'!B18 | C23: ='India Assumptions'!B19
A24: Customer lifetime (yrs) | B24: =1/B23 | C24: =1/C23
A25: LTV (gross margin) | B25: =B11*B24 | C25: =C11*C24 | D25: =(B25*$F$4+C25*$F$5)/($F$4+$F$5)
A26: LTV:CAC (gross) | B26: =B25/B14 | C26: =C25/C14 | D26: =D25/D14
A27: LTV:CAC (net CAC) | B27: =B25/B17 | C27: =C25/C17 | D27: =D25/D17
A29: Note: SMB excludes CAD compute (SMB = non-3D tiers). Mid = Digital Twin tier (CAD applies).
